<?xml version="1.0" encoding="UTF-8"?>
<beans:beans xmlns:beans="http://www.springframework.org/schema/beans"
	xmlns="http://www.springframework.org/schema/security" 
	xmlns:xsi="http://www.w3.org/2001/XMLSchema-instance"
	xsi:schemaLocation="http://www.springframework.org/schema/beans
        http://www.springframework.org/schema/beans/spring-beans.xsd
		http://www.springframework.org/schema/security
		http://www.springframework.org/schema//security/spring-security.xsd">
		
		
		
		
		
		<http>
			<form-login 
				login-page="/joinus/login"
				default-target-url="/home/index"/>
			
			<logout logout-success-url="/home/index"/>
			<intercept-url pattern="/findpartner/userlist" access="ROLE_ADMIN"/>
			<intercept-url pattern="/mypage/mypage" access="ROLE_ADMIN"/>
		</http>
		
		<authentication-manager>
			<!-- 사용자 정보 제공할 부분 -->
			<authentication-provider>
			<jdbc-user-service data-source-ref="dataSource"
				users-by-username-query="SELECT mid userid, pwd password, 1 enabled From Members WHERE mid=?"
				authorities-by-username-query="SELECT mid userid, 'ROLE_ADMIN' authorities From Members WHERE mid=?"
				/>
				<!-- <user-service>
					<user name="dragon" password="111" authorities="ROLE_TEACHER"/>
					<user name="wsquser" password="mansoo" authorities="ROLE_TEACHER, ROLE_ADMIN"/>
				</user-service> -->
			</authentication-provider>
		</authentication-manager>
		
</beans:beans>